sweetcurves/__init__.py
sweetcurves/catelog/__init__.py
sweetcurves/catelog/cloud.py
sweetcurves/catelog/stack.py
sweetcurves/cloud_build.py
sweetcurves/commands.py
sweetcurves/complete.py
sweetcurves/helpers.py
sweetcurves/main.py
sweetcurves/paths.py
sweetcurves/stack.yml
sweetcurves/stackset.py
sweetcurves/utils.py
sweetcurves-0.1.7.dist-info/entry_points.txt
sweetcurves-0.1.7.dist-info/WHEEL
sweetcurves-0.1.7.dist-info/METADATA
sweetcurves-0.1.7.dist-info/RECORD
