Metadata-Version: 2.1
Name: sweetcurves
Version: 0.1.7
Summary: Slight build automation and changes.
Author: Kevin Hill
Author-email: kah.kevin.hill@gmail.com
Requires-Python: >=3.7.0,<4.0.0
Classifier: Programming Language :: Python :: 3
Classifier: Programming Language :: Python :: 3.7
Classifier: Programming Language :: Python :: 3.8
Classifier: Programming Language :: Python :: 3.9
Requires-Dist: PyYAML (>=5.4.1,<6.0.0)
Requires-Dist: decorator (>=4.4.2,<5.0.0)
Requires-Dist: devtools (>=0.6.1,<0.7.0)
Requires-Dist: loguru (>=0.5.3,<0.6.0)
Requires-Dist: pydantic (>=1.8.1,<2.0.0)
Requires-Dist: pyperclip (>=1.8.2,<2.0.0)
Requires-Dist: sh (>=1.14.1,<2.0.0)
Requires-Dist: toolz (>=0.11.0,<0.12.0)
Requires-Dist: typer[all] (>=0.3.2,<0.4.0)
